{
	"$schema": "http://json-schema.org/draft-07/schema",
	"type": "object",
	"properties": {
		"minecraft:camera_preset": {
			"title": "Camera Preset Definition",
			"required": [
				"identifier"
			],
			"type": "object",
			"allOf": [
				{
					"properties": {
						"identifier": {
							"title": "Identifier",
							"$ref": "../../general/reference/prefixedFileIdentifier.json",
							"description": "The identifier for this camera preset. The name must include a namespace and must not use the Minecraft namespace."
						},
						"inherit_from": {
							"title": "Camera Inheritor",
							"description": "Inherits the properties of the specified camera preset.",
							"$ref": "../../general/reference/identifiers.json#/definitions/camera_preset_identifiers"
						}
					}
				},
				{
					"properties": {
						"listener": {
							"title": "Listener",
							"description": "Specify 'camera' or 'player' to control whether the camera or player is used for audio listening position when this preset is active.",
							"type": "string",
							"enum": [
								"camera",
								"player"
							]
						},
						"player_effects": {
							"title": "Player Effects",
							"description": "Specify whether to allow effects on the player to affect how the game renders when this preset is active.",
							"type": "boolean"
						},
						"pos_x": {
							"title": "X Position",
							"description": "Set an X position for this camera's behavior.",
							"type": "integer"
						},
						"pos_y": {
							"title": "Y Position",
							"description": "Set a Y position for this camera's behavior.",
							"type": "integer"
						},
						"pos_z": {
							"title": "Z Position",
							"description": "Set a Z position for this camera's behavior.",
							"type": "integer"
						},
						"rot_x": {
							"title": "X Rotation",
							"description": "Set an X rotation for this camera's behavior.",
							"type": "integer",
							"minimum": -90,
							"maximum": 90
						},
						"rot_y": {
							"title": "Y Rotation",
							"description": "Set a Y rotation for this camera's behavior.",
							"minimum": -360,
							"maximum": 360
						}
					}
				}
			]
		}
	}
}